Workbook
Name Slicer_City: #N/A
Name Slicer_Payment_Mode: #N/A
Name Slicer_Product: #N/A

Sheet Sales Data
A1: Order ID | B1: Order Date | C1: Month | D1: Customer ID | E1: Product | F1: Category | G1: Quantity | H1: Unit Price | I1: Revenue | J1: Cost | K1: Profit | L1: Payment Mode | M1: City
A2: ORD001 | B2: 2025-01-09 | C2: =TEXT(B2,"MMM-YYYY") -> Jan-2025 | D2: C016 | E2: Jeans | F2: Clothing | G2: 1 | H2: 2500 | I2: 2500 | J2: 1800 | K2: 700 | L2: Card | M2: Faisalabad
A3: ORD002 | B3: 2025-01-26 | C3: =TEXT(B3,"MMM-YYYY") -> Jan-2025 | D3: C027 | E3: Sneakers | F3: Footwear | G3: 4 | H3: 4000 | I3: 16000 | J3: 12000 | K3: 4000 | L3: COD | M3: Faisalabad
A4: ORD003 | B4: 2025-01-14 | C4: =TEXT(B4,"MMM-YYYY") -> Jan-2025 | D4: C078 | E4: T-Shirt | F4: Clothing | G4: 4 | H4: 1200 | I4: 4800 | J4: 3200 | K4: 1600 | L4: COD | M4: Peshawar
A5: ORD004 | B5: 2025-01-24 | C5: =TEXT(B5,"MMM-YYYY") -> Jan-2025 | D5: C103 | E5: Sneakers | F5: Footwear | G5: 3 | H5: 4000 | I5: 12000 | J5: 9000 | K5: 3000 | L5: COD | M5: Multan
A6: ORD005 | B6: 2025-01-01 | C6: =TEXT(B6,"MMM-YYYY") -> Jan-2025 | D6: C003 | E6: T-Shirt | F6: Clothing | G6: 3 | H6: 1200 | I6: 3600 | J6: 2400 | K6: 1200 | L6: COD | M6: Peshawar
A7: ORD006 | B7: 2025-01-29 | C7: =TEXT(B7,"MMM-YYYY") -> Jan-2025 | D7: C049 | E7: Sandals | F7: Footwear | G7: 1 | H7: 1800 | I7: 1800 | J7: 1200 | K7: 600 | L7: Wallet | M7: Lahore
A8: ORD007 | B8: 2025-01-17 | C8: =TEXT(B8,"MMM-YYYY") -> Jan-2025 | D8: C029 | E8: Sneakers | F8: Footwear | G8: 1 | H8: 4000 | I8: 4000 | J8: 3000 | K8: 1000 | L8: Card | M8: Faisalabad
A9: ORD008 | B9: 2025-01-12 | C9: =TEXT(B9,"MMM-YYYY") -> Jan-2025 | D9: C030 | E9: Sandals | F9: Footwear | G9: 2 | H9: 1800 | I9: 3600 | J9: 2400 | K9: 1200 | L9: Wallet | M9: Lahore
A10: ORD009 | B10: 2025-01-30 | C10: =TEXT(B10,"MMM-YYYY") -> Jan-2025 | D10: C003 | E10: Sneakers | F10: Footwear | G10: 3 | H10: 4000 | I10: 12000 | J10: 9000 | K10: 3000 | L10: Card | M10: Multan
A11: ORD010 | B11: 2025-01-06 | C11: =TEXT(B11,"MMM-YYYY") -> Jan-2025 | D11: C081 | E11: Cap | F11: Accessories | G11: 1 | H11: 800 | I11: 800 | J11: 400 | K11: 400 | L11: Wallet | M11: Islamabad
A12: ORD011 | B12: 2025-01-29 | C12: =TEXT(B12,"MMM-YYYY") -> Jan-2025 | D12: C093 | E12: T-Shirt | F12: Clothing | G12: 3 | H12: 1200 | I12: 3600 | J12: 2400 | K12: 1200 | L12: Wallet | M12: Multan
A13: ORD012 | B13: 2025-01-10 | C13: =TEXT(B13,"MMM-YYYY") -> Jan-2025 | D13: C037 | E13: Sneakers | F13: Footwear | G13: 2 | H13: 4000 | I13: 8000 | J13: 6000 | K13: 2000 | L13: Wallet | M13: Faisalabad
... A201: ORD200 | B201: 2025-01-15 | C201: =TEXT(B201,"MMM-YYYY") -> Jan-2025 | D201: C077 | E201: Sneakers | F201: Footwear | G201: 3 | H201: 4000 | I201: 12000 | J201: 9000 | K201: 3000 | L201: Card | M201: Multan

Sheet Dashboard
B5: ='Sales Analysis'!A4 -> 200 | Q5: =GETPIVOTDATA("Total Sales",'Sales Analysis'!$A$3)/GETPIVOTDATA("Total Order",'Sales Analysis'!$A$3) -> 5487
F6: =GETPIVOTDATA("Total Sales",'Sales Analysis'!$A$3) -> 1097400 | K6: =GETPIVOTDATA("Order ID",'Sales Analysis'!$A$8,"Delivery Status","Delivered") -> 177 | O6: =GETPIVOTDATA("Order ID",'Sales Analysis'!$A$8,"Delivery Status","Pending") -> 23

Sheet Sales Analysis
A1: TOTAL SALES & ORDERS | D1: SALES BY CITY
A3: Total Order | B3: Total Sales | D3: Row Labels | E3: Sum of Revenue | F3: Count of Order ID
A4: 200 | B4: 1097400 | D4: Faisalabad | E4: 45000 | F4: 7
D5: Islamabad | E5: 42500 | F5: 6
A6: DELIVERY STATUS | D6: Karachi | E6: 25000 | F6: 4
D7: Lahore | E7: 17500 | F7: 3
A8: Delivery Status | B8: Count of Order ID | D8: Multan | E8: 40000 | F8: 6
A9: Delivered | B9: 177 | D9: Peshawar | E9: 35000 | F9: 6
A10: Pending | B10: 23 | D10: Grand Total | E10: 205000 | F10: 32
A11: Grand Total | B11: 200
A13: PAYMENT MODE
A15: Row Labels | B15: Count of Order ID
A16: Card | B16: 70
A17: COD | B17: 65
A18: Wallet | B18: 65
A19: Grand Total | B19: 200
A21: SALES BY PRODUCT
A23: Row Labels | B23: Sum of Revenue
A24: Cap | B24: 78400
A25: Hoodie | B25: 213000
A26: Jeans | B26: 205000
A27: Sandals | B27: 178200
A28: Sneakers | B28: 328000
A29: T-Shirt | B29: 94800
A30: Grand Total | B30: 1097400

Sheet Invioce
B1: INVIOCE
B2: E-commerce Store
B4: Order ID : | C4: ORD003 | E4: Date : | F4: =TODAY() -> 46049
E5: Invioce #
B7: BILL TO :
B10: Customer ID : | C10: =_xlfn.XLOOKUP($C$4,'Sales Data'!A:A,'Sales Data'!D:D, "Not Found") -> C078
B11: City : | C11: =_xlfn.XLOOKUP($C$4,'Sales Data'!A:A,'Sales Data'!M:M) -> Peshawar
B12: Payment Mode : | C12: =_xlfn.XLOOKUP($C$4,'Sales Data'!A:A,'Sales Data'!L:L) -> COD
B14: Product | C14: Quantity | D14: Unit Price | E14: Total | F14: Discount
B15: =_xlfn.XLOOKUP($C$4,'Sales Data'!A:A,'Sales Data'!E:E) -> T-Shirt | C15: =_xlfn.XLOOKUP($C$4,'Sales Data'!A:A,'Sales Data'!G:G) -> 4 | D15: =_xlfn.XLOOKUP($C$4,'Sales Data'!A:A,'Sales Data'!H:H) -> 1200 | E15: =C15*D15 -> 4800 | F15: 0.1
B16: - | C16: - | D16: - | E16: - | F16: -
B17: - | C17: - | D17: - | E17: - | F17: -
B18: - | C18: - | D18: - | E18: - | F18: -
B19: - | C19: - | D19: - | E19: - | F19: -
B20: Grand Total | D20: =E15*(1-F15) -> 4320

Sheet Search Bar
C2: Search Bar | D2: ORD017
C4: Order ID | D4: Order Date | E4: Month | F4: Customer ID | G4: Product | H4: Category | I4: Quantity | J4: Unit Price | K4: Revenue | L4: Cost | M4: Profit | N4: Payment Mode | O4: City
C5: {=_xlfn._xlws.FILTER(Table1[],ISNUMBER(SEARCH(D2,Table1[Order ID])))} -> ORD017 | D5: 2025-01-16 | E5: Jan-2025 | F5: C006 | G5: Sneakers | H5: Footwear | I5: 1 | J5: 4000 | K5: 4000 | L5: 3000 | M5: 1000 | N5: Card | O5: Peshawar

Sheet Delivery_Tracking
A1: Delivery Tracking
A2: Order ID | B2: Customer ID | C2: Product | D2: Quantity | E2: Delivered | F2: Delivery Status
A3: {=Table1[Order ID]} -> ORD001 | B3: {=Table1[Customer ID]} -> C016 | C3: {=Table1[Product]} -> Jeans | D3: {=Table1[Quantity]} -> 1 | E3: TRUE | F3: =IF(E3=TRUE,"Delivered","Pending") -> Delivered
A4: ORD002 | B4: C027 | C4: Sneakers | D4: 4 | E4: TRUE | F4: =IF(E4=TRUE,"Delivered","Pending") -> Delivered
A5: ORD003 | B5: C078 | C5: T-Shirt | D5: 4 | E5: FALSE | F5: =IF(E5=TRUE,"Delivered","Pending") -> Pending
A6: ORD004 | B6: C103 | C6: Sneakers | D6: 3 | E6: TRUE | F6: =IF(E6=TRUE,"Delivered","Pending") -> Delivered
A7: ORD005 | B7: C003 | C7: T-Shirt | D7: 3 | E7: TRUE | F7: =IF(E7=TRUE,"Delivered","Pending") -> Delivered
A8: ORD006 | B8: C049 | C8: Sandals | D8: 1 | E8: TRUE | F8: =IF(E8=TRUE,"Delivered","Pending") -> Delivered
A9: ORD007 | B9: C029 | C9: Sneakers | D9: 1 | E9: FALSE | F9: =IF(E9=TRUE,"Delivered","Pending") -> Pending
A10: ORD008 | B10: C030 | C10: Sandals | D10: 2 | E10: TRUE | F10: =IF(E10=TRUE,"Delivered","Pending") -> Delivered
A11: ORD009 | B11: C003 | C11: Sneakers | D11: 3 | E11: TRUE | F11: =IF(E11=TRUE,"Delivered","Pending") -> Delivered
A12: ORD010 | B12: C081 | C12: Cap | D12: 1 | E12: TRUE | F12: =IF(E12=TRUE,"Delivered","Pending") -> Delivered
A13: ORD011 | B13: C093 | C13: T-Shirt | D13: 3 | E13: FALSE | F13: =IF(E13=TRUE,"Delivered","Pending") -> Pending
A14: ORD012 | B14: C037 | C14: Sneakers | D14: 2 | E14: TRUE | F14: =IF(E14=TRUE,"Delivered","Pending") -> Delivered
A15: ORD013 | B15: C110 | C15: Sandals | D15: 4 | E15: TRUE | F15: =IF(E15=TRUE,"Delivered","Pending") -> Delivered
... A202: ORD200 | B202: C077 | C202: Sneakers | D202: 3 | E202: FALSE | F202: =IF(E202=TRUE,"Delivered","Pending") -> Pending

Sheet Inventory_Tracking
A1: INVENTORY
A2: Product | B2: Category | C2: Opening Stock | D2: Sold Quantity | E2: Available Stock | F2: Stock Status
A3: Cap | B3: Accessories | C3: 200 | D3: =GETPIVOTDATA("Quantity", Inventory_Tracking!$H$6, "Product", A3) -> 98 | E3: =C3-D3 -> 102 | F3: =IF(E3<=10,"Low Stock","In Stock") -> In Stock
A4: Hoodie | B4: Clothing | C4: 120 | D4: =GETPIVOTDATA("Quantity", Inventory_Tracking!$H$6, "Product", A4) -> 71 | E4: =C4-D4 -> 49 | F4: =IF(E4<=10,"Low Stock","In Stock") -> In Stock | H4: Row Labels | I4: Sum of Profit | J4: Sum of Revenue | K4: Sum of Quantity
A5: Jeans | B5: Clothing | C5: 150 | D5: =GETPIVOTDATA("Quantity", Inventory_Tracking!$H$6, "Product", A5) -> 82 | E5: =C5-D5 -> 68 | F5: =IF(E5<=10,"Low Stock","In Stock") -> In Stock | H5: Cap | I5: 39200 | J5: 78400 | K5: 98
A6: Sandals | B6: Footwear | C6: 100 | D6: =GETPIVOTDATA("Quantity", Inventory_Tracking!$H$6, "Product", A6) -> 99 | E6: =C6-D6 -> 1 | F6: =IF(E6<=10,"Low Stock","In Stock") -> Low Stock | H6: Hoodie | I6: 56800 | J6: 213000 | K6: 71
A7: Sneakers | B7: Footwear | C7: 300 | D7: =GETPIVOTDATA("Quantity", Inventory_Tracking!$H$6, "Product", A7) -> 82 | E7: =C7-D7 -> 218 | F7: =IF(E7<=10,"Low Stock","In Stock") -> In Stock | H7: Jeans | I7: 57400 | J7: 205000 | K7: 82
A8: T-Shirt | B8: Clothing | C8: 100 | D8: =GETPIVOTDATA("Quantity", Inventory_Tracking!$H$6, "Product", A8) -> 79 | E8: =C8-D8 -> 21 | F8: =IF(E8<=10,"Low Stock","In Stock") -> In Stock | H8: Sandals | I8: 59400 | J8: 178200 | K8: 99
H9: Sneakers | I9: 82000 | J9: 328000 | K9: 82
H10: T-Shirt | I10: 31600 | J10: 94800 | K10: 79
