Workbook

Sheet Settings
A1: Opening Cash Balance | B1: 10000
D5: Row Labels | E5: Sum of Amount
D6: Marketing | E6: 3956
D7: Rent | E7: 8631
D8: Salaries | E8: 10167
D9: Software | E9: 1275
D10: Utilities | E10: 7623
D11: Grand Total | E11: 31652

Sheet Income_DB
A1: Income_ID | B1: Date | C1: Source | D1: Category | E1: Description | F1: Amount | G1: Payment_Mode
A2: INC001 | B2: 46153 | C2: Online Store | D2: Consulting | E2: Business income | F2: 1355 | G2: Cash
A3: INC002 | B3: 46194 | C3: Client C | D3: Subscription | E3: Business income | F3: 1432 | G3: Card
A4: INC003 | B4: 46039 | C4: Client C | D4: Consulting | E4: Business income | F4: 1314 | G4: Card
A5: INC004 | B5: 46183 | C5: Client A | D5: Subscription | E5: Business income | F5: 172 | G5: Cash
A6: INC005 | B6: 46153 | C6: Online Store | D6: Subscription | E6: Business income | F6: 705 | G6: Bank
A7: INC006 | B7: 46201 | C7: Online Store | D7: Services | E7: Business income | F7: 854 | G7: Card
A8: INC007 | B8: 46052 | C8: Client A | D8: Sales | E8: Business income | F8: 756 | G8: Card
A9: INC008 | B9: 46166 | C9: Online Store | D9: Sales | E9: Business income | F9: 1125 | G9: Bank
A10: INC009 | B10: 46131 | C10: Client B | D10: Sales | E10: Business income | F10: 381 | G10: Bank
A11: INC010 | B11: 46186 | C11: Online Store | D11: Sales | E11: Business income | F11: 957 | G11: Cash
A12: INC011 | B12: 46136 | C12: Corporate Client | D12: Sales | E12: Business income | F12: 269 | G12: Bank
A13: INC012 | B13: 46173 | C13: Online Store | D13: Sales | E13: Business income | F13: 481 | G13: Bank
... A51: INC050 | B51: 46085 | C51: Corporate Client | D51: Consulting | E51: Business income | F51: 714 | G51: Cash

Sheet Expense_DB
A1: Expense_ID | B1: Date | C1: Vendor | D1: Category | E1: Description | F1: Amount | G1: Payment_Mode
A2: EXP001 | B2: 46198 | C2: Facebook Ads | D2: Salaries | E2: Business expense | F2: 908 | G2: Cash
A3: EXP002 | B3: 46030 | C3: Electricity Dept | D3: Marketing | E3: Business expense | F3: 1053 | G3: Cash
A4: EXP003 | B4: 46127 | C4: Electricity Dept | D4: Marketing | E4: Business expense | F4: 596 | G4: Card
A5: EXP004 | B5: 46116 | C5: Electricity Dept | D5: Utilities | E5: Business expense | F5: 358 | G5: Cash
A6: EXP005 | B6: 46040 | C6: Software Tools | D6: Salaries | E6: Business expense | F6: 1193 | G6: Cash
A7: EXP006 | B7: 46123 | C7: Internet Co | D7: Rent | E7: Business expense | F7: 117 | G7: Card
A8: EXP007 | B8: 46056 | C8: Facebook Ads | D8: Rent | E8: Business expense | F8: 187 | G8: Bank
A9: EXP008 | B9: 46128 | C9: Internet Co | D9: Rent | E9: Business expense | F9: 437 | G9: Cash
A10: EXP009 | B10: 46027 | C10: Internet Co | D10: Utilities | E10: Business expense | F10: 1080 | G10: Cash
A11: EXP010 | B11: 46102 | C11: Software Tools | D11: Rent | E11: Business expense | F11: 242 | G11: Cash
A12: EXP011 | B12: 46087 | C12: Electricity Dept | D12: Salaries | E12: Business expense | F12: 820 | G12: Bank
A13: EXP012 | B13: 46166 | C13: Electricity Dept | D13: Software | E13: Business expense | F13: 244 | G13: Card
... A51: EXP050 | B51: 46113 | C51: Office Rent | D51: Utilities | E51: Business expense | F51: 655 | G51: Card

Sheet Cash_Flow
A1: Month | B1: Total Income | C1: Total Expense | D1: Net Cash Flow | E1: Cash Balance
A2: =TEXT(DATE(2026,ROW(A1),1),"mmm-yyyy") -> Jan-2026 | B2: =SUMIFS(Income_DB!F:F,Income_DB!B:B,">="&EOMONTH(DATE(2026,ROW(A1),1),-1)+1, Income_DB!B:B,"<="&EOMONTH(DATE(2026,ROW(A1),1),0)) -> 7085 | C2: =SUMIFS(Expense_DB!F:F,Expense_DB!B:B,">="&EOMONTH(DATE(2026,ROW(A1),1),-1)+1, Expense_DB!B:B,"<="&EOMONTH(DATE(2026,ROW(A1),1),0)) -> 6666 | D2: =B2-C2 -> 419 | E2: =Settings!B1 + D2 -> 10419
A3: =TEXT(DATE(2026,ROW(A2),1),"mmm-yyyy") -> Feb-2026 | B3: =SUMIFS(Income_DB!F:F,Income_DB!B:B,">="&EOMONTH(DATE(2026,ROW(A2),1),-1)+1, Income_DB!B:B,"<="&EOMONTH(DATE(2026,ROW(A2),1),0)) -> 4239 | C3: =SUMIFS(Expense_DB!F:F,Expense_DB!B:B,">="&EOMONTH(DATE(2026,ROW(A2),1),-1)+1, Expense_DB!B:B,"<="&EOMONTH(DATE(2026,ROW(A2),1),0)) -> 4252 | D3: =B3-C3 -> -13 | E3: =E2 + D3 -> 10406
A4: =TEXT(DATE(2026,ROW(A3),1),"mmm-yyyy") -> Mar-2026 | B4: =SUMIFS(Income_DB!F:F,Income_DB!B:B,">="&EOMONTH(DATE(2026,ROW(A3),1),-1)+1, Income_DB!B:B,"<="&EOMONTH(DATE(2026,ROW(A3),1),0)) -> 4005 | C4: =SUMIFS(Expense_DB!F:F,Expense_DB!B:B,">="&EOMONTH(DATE(2026,ROW(A3),1),-1)+1, Expense_DB!B:B,"<="&EOMONTH(DATE(2026,ROW(A3),1),0)) -> 6656 | D4: =B4-C4 -> -2651 | E4: =E3 + D4 -> 7755
A5: =TEXT(DATE(2026,ROW(A4),1),"mmm-yyyy") -> Apr-2026 | B5: =SUMIFS(Income_DB!F:F,Income_DB!B:B,">="&EOMONTH(DATE(2026,ROW(A4),1),-1)+1, Income_DB!B:B,"<="&EOMONTH(DATE(2026,ROW(A4),1),0)) -> 3974 | C5: =SUMIFS(Expense_DB!F:F,Expense_DB!B:B,">="&EOMONTH(DATE(2026,ROW(A4),1),-1)+1, Expense_DB!B:B,"<="&EOMONTH(DATE(2026,ROW(A4),1),0)) -> 4378 | D5: =B5-C5 -> -404 | E5: =E4 + D5 -> 7351
A6: =TEXT(DATE(2026,ROW(A5),1),"mmm-yyyy") -> May-2026 | B6: =SUMIFS(Income_DB!F:F,Income_DB!B:B,">="&EOMONTH(DATE(2026,ROW(A5),1),-1)+1, Income_DB!B:B,"<="&EOMONTH(DATE(2026,ROW(A5),1),0)) -> 7424 | C6: =SUMIFS(Expense_DB!F:F,Expense_DB!B:B,">="&EOMONTH(DATE(2026,ROW(A5),1),-1)+1, Expense_DB!B:B,"<="&EOMONTH(DATE(2026,ROW(A5),1),0)) -> 5153 | D6: =B6-C6 -> 2271 | E6: =E5 + D6 -> 9622
A7: =TEXT(DATE(2026,ROW(A6),1),"mmm-yyyy") -> Jun-2026 | B7: =SUMIFS(Income_DB!F:F,Income_DB!B:B,">="&EOMONTH(DATE(2026,ROW(A6),1),-1)+1, Income_DB!B:B,"<="&EOMONTH(DATE(2026,ROW(A6),1),0)) -> 9125 | C7: =SUMIFS(Expense_DB!F:F,Expense_DB!B:B,">="&EOMONTH(DATE(2026,ROW(A6),1),-1)+1, Expense_DB!B:B,"<="&EOMONTH(DATE(2026,ROW(A6),1),0)) -> 4547 | D7: =B7-C7 -> 4578 | E7: =E6 + D7 -> 14200
A8: =TEXT(DATE(2026,ROW(A7),1),"mmm-yyyy") -> Jul-2026 | B8: =SUMIFS(Income_DB!F:F,Income_DB!B:B,">="&EOMONTH(DATE(2026,ROW(A7),1),-1)+1, Income_DB!B:B,"<="&EOMONTH(DATE(2026,ROW(A7),1),0)) -> 0 | C8: =SUMIFS(Expense_DB!F:F,Expense_DB!B:B,">="&EOMONTH(DATE(2026,ROW(A7),1),-1)+1, Expense_DB!B:B,"<="&EOMONTH(DATE(2026,ROW(A7),1),0)) -> 0 | D8: =B8-C8 -> 0 | E8: =E7 + D8 -> 14200
A9: =TEXT(DATE(2026,ROW(A8),1),"mmm-yyyy") -> Aug-2026 | B9: =SUMIFS(Income_DB!F:F,Income_DB!B:B,">="&EOMONTH(DATE(2026,ROW(A8),1),-1)+1, Income_DB!B:B,"<="&EOMONTH(DATE(2026,ROW(A8),1),0)) -> 0 | C9: =SUMIFS(Expense_DB!F:F,Expense_DB!B:B,">="&EOMONTH(DATE(2026,ROW(A8),1),-1)+1, Expense_DB!B:B,"<="&EOMONTH(DATE(2026,ROW(A8),1),0)) -> 0 | D9: =B9-C9 -> 0 | E9: =E8 + D9 -> 14200
A10: =TEXT(DATE(2026,ROW(A9),1),"mmm-yyyy") -> Sep-2026 | B10: =SUMIFS(Income_DB!F:F,Income_DB!B:B,">="&EOMONTH(DATE(2026,ROW(A9),1),-1)+1, Income_DB!B:B,"<="&EOMONTH(DATE(2026,ROW(A9),1),0)) -> 0 | C10: =SUMIFS(Expense_DB!F:F,Expense_DB!B:B,">="&EOMONTH(DATE(2026,ROW(A9),1),-1)+1, Expense_DB!B:B,"<="&EOMONTH(DATE(2026,ROW(A9),1),0)) -> 0 | D10: =B10-C10 -> 0 | E10: =E9 + D10 -> 14200
A11: =TEXT(DATE(2026,ROW(A10),1),"mmm-yyyy") -> Oct-2026 | B11: =SUMIFS(Income_DB!F:F,Income_DB!B:B,">="&EOMONTH(DATE(2026,ROW(A10),1),-1)+1, Income_DB!B:B,"<="&EOMONTH(DATE(2026,ROW(A10),1),0)) -> 0 | C11: =SUMIFS(Expense_DB!F:F,Expense_DB!B:B,">="&EOMONTH(DATE(2026,ROW(A10),1),-1)+1, Expense_DB!B:B,"<="&EOMONTH(DATE(2026,ROW(A10),1),0)) -> 0 | D11: =B11-C11 -> 0 | E11: =E10 + D11 -> 14200
A12: =TEXT(DATE(2026,ROW(A11),1),"mmm-yyyy") -> Nov-2026 | B12: =SUMIFS(Income_DB!F:F,Income_DB!B:B,">="&EOMONTH(DATE(2026,ROW(A11),1),-1)+1, Income_DB!B:B,"<="&EOMONTH(DATE(2026,ROW(A11),1),0)) -> 0 | C12: =SUMIFS(Expense_DB!F:F,Expense_DB!B:B,">="&EOMONTH(DATE(2026,ROW(A11),1),-1)+1, Expense_DB!B:B,"<="&EOMONTH(DATE(2026,ROW(A11),1),0)) -> 0 | D12: =B12-C12 -> 0 | E12: =E11 + D12 -> 14200
A13: =TEXT(DATE(2026,ROW(A12),1),"mmm-yyyy") -> Dec-2026 | B13: =SUMIFS(Income_DB!F:F,Income_DB!B:B,">="&EOMONTH(DATE(2026,ROW(A12),1),-1)+1, Income_DB!B:B,"<="&EOMONTH(DATE(2026,ROW(A12),1),0)) -> 0 | C13: =SUMIFS(Expense_DB!F:F,Expense_DB!B:B,">="&EOMONTH(DATE(2026,ROW(A12),1),-1)+1, Expense_DB!B:B,"<="&EOMONTH(DATE(2026,ROW(A12),1),0)) -> 0 | D13: =B13-C13 -> 0 | E13: =E12 + D13 -> 14200

Sheet Monthly_Summary
A1: KPI Board
A2: Total Income | B2: =SUM(Income_DB!F:F) -> 35852
A3: Total Expense | B3: =SUM(Expense_DB!F:F) -> 31652
A4: Net Profit | B4: =B2-B3 -> 4200
A5: Profit % | B5: =B4/B3 -> 0.13269304
A6: Avg Monthly Burn | B6: =ABS(AVERAGEIF(Cash_Flow!D:D,"<0")) -> 1022.6667
A7: Runway (Months) | B7: =IF(B5>0,"Profitable",Settings!B1/B6) -> Profitable

Sheet Dashboard
